myconsole/__init__.py
myconsole/console.py
myconsole/demo.py
myconsole/embed.py
myconsole-1.0.2.dist-info/DESCRIPTION.rst
myconsole-1.0.2.dist-info/METADATA
myconsole-1.0.2.dist-info/RECORD
myconsole-1.0.2.dist-info/WHEEL
myconsole-1.0.2.dist-info/entry_points.txt
myconsole-1.0.2.dist-info/metadata.json
myconsole-1.0.2.dist-info/top_level.txt
