Metadata-Version: 2.0
Name: myconsole
Version: 1.0.2
Summary: create IPython consoles with custom banners
Home-page: https://github.com/haarcuba/myconsole
Author: Yoav Kleinberger
Author-email: haarcuba@gmail.com
License: UNKNOWN
Platform: UNKNOWN
Classifier: Programming Language :: Python
Requires-Dist: ipython (==5.3.0)
